setup.py
cypher_library_python_core_20/__init__.py
cypher_library_python_core_20/xor_utility.py
cypher_library_python_core_20.egg-info/PKG-INFO
cypher_library_python_core_20.egg-info/SOURCES.txt
cypher_library_python_core_20.egg-info/dependency_links.txt
cypher_library_python_core_20.egg-info/top_level.txt