Metadata-Version: 2.1
Name: cypher-library-python-core-20
Version: 0.1
Summary: Cypher library for python core 20 students
Home-page: UNKNOWN
Author: Dimka Kushchevskyi
Author-email: dima.kushhevskij@gmail.com
License: MIT
Platform: UNKNOWN
